aio_binance/__init__.py
aio_binance/__version__.py
aio_binance/timer.py
aio_binance/error_handler/__init__.py
aio_binance/error_handler/error.py
aio_binance/futures/__init__.py
aio_binance/futures/usdt/__init__.py
aio_binance/futures/usdt/api/__init__.py
aio_binance/futures/usdt/api/manager.py
aio_binance/futures/usdt/api/query.py
aio_binance/futures/usdt/api/methods/__init__.py
aio_binance/futures/usdt/api/methods/account.py
aio_binance/futures/usdt/api/methods/market.py
aio_binance/futures/usdt/api/methods/stream.py
aio_binance/futures/usdt/websocket/__init__.py
aio_binance/futures/usdt/websocket/account.py
aio_binance/futures/usdt/websocket/query.py
aio_binance/futures/usdt/websocket/streams.py
aio_binance_library-2.0.7.dist-info/METADATA
aio_binance_library-2.0.7.dist-info/WHEEL
aio_binance_library-2.0.7.dist-info/top_level.txt
aio_binance_library-2.0.7.dist-info/RECORD
